Workbook

Sheet Instructions
B2: Amazon UK Acquisition P&L — TEMPLATE
B3: Attach this workbook + the Workflow doc at the start of a new chat, upload the source files, and Claude fills it step by step.
B5: How this template works
B6: • This template is INPUT-DRIVEN: fill the blue cells on the 'Inputs_*' tabs and the P&L + Summary compute automatically.
B7: • It is pre-filled with DUMMY data (same figures each month) purely to show the format — overwrite every blue cell with real data.
B8: • Blue = input you fill · Black = formula (leave it) · Green = pulled from another tab · Yellow = editable assumption.
B9: • The dummy data already reconciles (the two 'check: Difference' rows on the P&L are 0) — keep them at 0 with real data too.
B11: What to put on each tab
B12: • Inputs_Monthly — one row per month; every Income & Expense line straight from the monthly Summary PDF (incl. the printed Income total & Expenses total, used for the reconciliation checks).
B13: • Inputs_Units — units sold per SKU per month (net = orders − refunds, from the transaction CSVs). Each SKU's £/unit references the editable COST RATE TABLE (right). Monthly COGS computes at the bottom.
B14: • Inputs_Traffic — per month: sessions, page views, units ordered, Buy Box %, ASIN count (from Business Reports).
B15: • Assumptions (on the P&L) — VAT registered? (0/1), Off-Amazon operating cost £/month, and Asking Price (on Summary).
... B21: Golden rule: every month must tie to Amazon's own Income/Expenses totals (the check rows = 0) before trusting any number.

Sheet Inputs_Monthly
A1: Month | B1: ProductSales FBA | C1: ProductSales SF | D1: Refund FBA | E1: Refund SF | F1: Delivery credit refund | G1: Postage credits | H1: Inventory credit | I1: Gift-wrap credits | J1: Promo rebates | K1: Promo rebate refunds | L1: INCOME TOTAL | M1: FBA selling fees | N1: SF selling fees | O1: Selling fee refunds | P1: FBA transaction fees | Q1: FBA txn fee refunds | R1: Other txn fees | S1: Other txn fee refunds | T1: Storage & inbound | U1: Service fees | V1: Refund admin | W1: Delivery label | X1: Adjustments | Y1: Cost of Advertising | Z1: EXPENSES TOTAL
A2: M1 (oldest) | B2: 5000 | C2: 0 | D2: -150 | E2: 0 | F2: -5 | G2: 120 | H2: 30 | I2: 6 | J2: -100 | K2: 2 | L2: 4903 | M2: -750 | N2: 0 | O2: 5 | P2: -1200 | Q2: 3 | R2: -40 | S2: 0.5 | T2: -150 | U2: -30 | V2: -2 | W2: 0 | X2: 0 | Y2: -600 | Z2: -2763.5
A3: M2 | B3: 5000 | C3: 0 | D3: -150 | E3: 0 | F3: -5 | G3: 120 | H3: 30 | I3: 6 | J3: -100 | K3: 2 | L3: 4903 | M3: -750 | N3: 0 | O3: 5 | P3: -1200 | Q3: 3 | R3: -40 | S3: 0.5 | T3: -150 | U3: -30 | V3: -2 | W3: 0 | X3: 0 | Y3: -600 | Z3: -2763.5
A4: M3 | B4: 5000 | C4: 0 | D4: -150 | E4: 0 | F4: -5 | G4: 120 | H4: 30 | I4: 6 | J4: -100 | K4: 2 | L4: 4903 | M4: -750 | N4: 0 | O4: 5 | P4: -1200 | Q4: 3 | R4: -40 | S4: 0.5 | T4: -150 | U4: -30 | V4: -2 | W4: 0 | X4: 0 | Y4: -600 | Z4: -2763.5
A5: M4 | B5: 5000 | C5: 0 | D5: -150 | E5: 0 | F5: -5 | G5: 120 | H5: 30 | I5: 6 | J5: -100 | K5: 2 | L5: 4903 | M5: -750 | N5: 0 | O5: 5 | P5: -1200 | Q5: 3 | R5: -40 | S5: 0.5 | T5: -150 | U5: -30 | V5: -2 | W5: 0 | X5: 0 | Y5: -600 | Z5: -2763.5
A6: M5 | B6: 5000 | C6: 0 | D6: -150 | E6: 0 | F6: -5 | G6: 120 | H6: 30 | I6: 6 | J6: -100 | K6: 2 | L6: 4903 | M6: -750 | N6: 0 | O6: 5 | P6: -1200 | Q6: 3 | R6: -40 | S6: 0.5 | T6: -150 | U6: -30 | V6: -2 | W6: 0 | X6: 0 | Y6: -600 | Z6: -2763.5
A7: M6 | B7: 5000 | C7: 0 | D7: -150 | E7: 0 | F7: -5 | G7: 120 | H7: 30 | I7: 6 | J7: -100 | K7: 2 | L7: 4903 | M7: -750 | N7: 0 | O7: 5 | P7: -1200 | Q7: 3 | R7: -40 | S7: 0.5 | T7: -150 | U7: -30 | V7: -2 | W7: 0 | X7: 0 | Y7: -600 | Z7: -2763.5
A8: M7 | B8: 5000 | C8: 0 | D8: -150 | E8: 0 | F8: -5 | G8: 120 | H8: 30 | I8: 6 | J8: -100 | K8: 2 | L8: 4903 | M8: -750 | N8: 0 | O8: 5 | P8: -1200 | Q8: 3 | R8: -40 | S8: 0.5 | T8: -150 | U8: -30 | V8: -2 | W8: 0 | X8: 0 | Y8: -600 | Z8: -2763.5
A9: M8 | B9: 5000 | C9: 0 | D9: -150 | E9: 0 | F9: -5 | G9: 120 | H9: 30 | I9: 6 | J9: -100 | K9: 2 | L9: 4903 | M9: -750 | N9: 0 | O9: 5 | P9: -1200 | Q9: 3 | R9: -40 | S9: 0.5 | T9: -150 | U9: -30 | V9: -2 | W9: 0 | X9: 0 | Y9: -600 | Z9: -2763.5
A10: M9 | B10: 5000 | C10: 0 | D10: -150 | E10: 0 | F10: -5 | G10: 120 | H10: 30 | I10: 6 | J10: -100 | K10: 2 | L10: 4903 | M10: -750 | N10: 0 | O10: 5 | P10: -1200 | Q10: 3 | R10: -40 | S10: 0.5 | T10: -150 | U10: -30 | V10: -2 | W10: 0 | X10: 0 | Y10: -600 | Z10: -2763.5
A11: M10 | B11: 5000 | C11: 0 | D11: -150 | E11: 0 | F11: -5 | G11: 120 | H11: 30 | I11: 6 | J11: -100 | K11: 2 | L11: 4903 | M11: -750 | N11: 0 | O11: 5 | P11: -1200 | Q11: 3 | R11: -40 | S11: 0.5 | T11: -150 | U11: -30 | V11: -2 | W11: 0 | X11: 0 | Y11: -600 | Z11: -2763.5
A12: M11 | B12: 5000 | C12: 0 | D12: -150 | E12: 0 | F12: -5 | G12: 120 | H12: 30 | I12: 6 | J12: -100 | K12: 2 | L12: 4903 | M12: -750 | N12: 0 | O12: 5 | P12: -1200 | Q12: 3 | R12: -40 | S12: 0.5 | T12: -150 | U12: -30 | V12: -2 | W12: 0 | X12: 0 | Y12: -600 | Z12: -2763.5
A13: M12 | B13: 5000 | C13: 0 | D13: -150 | E13: 0 | F13: -5 | G13: 120 | H13: 30 | I13: 6 | J13: -100 | K13: 2 | L13: 4903 | M13: -750 | N13: 0 | O13: 5 | P13: -1200 | Q13: 3 | R13: -40 | S13: 0.5 | T13: -150 | U13: -30 | V13: -2 | W13: 0 | X13: 0 | Y13: -600 | Z13: -2763.5
A14: M13 (newest) | B14: 5000 | C14: 0 | D14: -150 | E14: 0 | F14: -5 | G14: 120 | H14: 30 | I14: 6 | J14: -100 | K14: 2 | L14: 4903 | M14: -750 | N14: 0 | O14: 5 | P14: -1200 | Q14: 3 | R14: -40 | S14: 0.5 | T14: -150 | U14: -30 | V14: -2 | W14: 0 | X14: 0 | Y14: -600 | Z14: -2763.5

Sheet Inputs_Units
A1: UNITS PER SKU PER MONTH (net = orders − refunds). £/unit pulls from the COST RATE TABLE (right).
R2: COST RATE TABLE (edit)
A3: SKU | B3: Family | C3: £/unit | D3: M1 (ol | E3: M2 | F3: M3 | G3: M4 | H3: M5 | I3: M6 | J3: M7 | K3: M8 | L3: M9 | M3: M10 | N3: M11 | O3: M12 | P3: M13 (n | R3: Family 1 | S3: 3
A4: DUMMY-SKU-A | B4: Family 1 | C4: =$S$3 -> 3 | D4: 100 | E4: 100 | F4: 100 | G4: 100 | H4: 100 | I4: 100 | J4: 100 | K4: 100 | L4: 100 | M4: 100 | N4: 100 | O4: 100 | P4: 100 | R4: Family 2 | S4: 5
A5: DUMMY-SKU-B | B5: Family 2 | C5: =$S$4 -> 5 | D5: 50 | E5: 50 | F5: 50 | G5: 50 | H5: 50 | I5: 50 | J5: 50 | K5: 50 | L5: 50 | M5: 50 | N5: 50 | O5: 50 | P5: 50 | R5: Family 3 | S5: 0.5
A6: DUMMY-SKU-C | B6: Family 3 | C6: =$S$5 -> 0.5 | D6: 200 | E6: 200 | F6: 200 | G6: 200 | H6: 200 | I6: 200 | J6: 200 | K6: 200 | L6: 200 | M6: 200 | N6: 200 | O6: 200 | P6: 200
R7: Add families/rates here; point each SKU's £/unit at the right rate cell.
A32: MONTHLY UNITS (total) | D32: =SUM(D4:D31) -> 350 | E32: =SUM(E4:E31) -> 350 | F32: =SUM(F4:F31) -> 350 | G32: =SUM(G4:G31) -> 350 | H32: =SUM(H4:H31) -> 350 | I32: =SUM(I4:I31) -> 350 | J32: =SUM(J4:J31) -> 350 | K32: =SUM(K4:K31) -> 350 | ... P32: =SUM(P4:P31) -> 350
A33: MONTHLY COGS (Σ units×rate) | D33: =SUMPRODUCT($C$4:$C$31,D4:D31) -> 650 | E33: =SUMPRODUCT($C$4:$C$31,E4:E31) -> 650 | F33: =SUMPRODUCT($C$4:$C$31,F4:F31) -> 650 | G33: =SUMPRODUCT($C$4:$C$31,G4:G31) -> 650 | H33: =SUMPRODUCT($C$4:$C$31,H4:H31) -> 650 | I33: =SUMPRODUCT($C$4:$C$31,I4:I31) -> 650 | J33: =SUMPRODUCT($C$4:$C$31,J4:J31) -> 650 | K33: =SUMPRODUCT($C$4:$C$31,K4:K31) -> 650 | ... P33: =SUMPRODUCT($C$4:$C$31,P4:P31) -> 650

Sheet Inputs_Traffic
A1: Month | B1: Sessions | C1: Page views | D1: Units ordered | E1: Buy Box % | F1: Child ASINs
A2: M1 (oldest) | B2: 3000 | C2: 4000 | D2: 350 | E2: 0.99 | F2: 10
A3: M2 | B3: 3000 | C3: 4000 | D3: 350 | E3: 0.99 | F3: 10
A4: M3 | B4: 3000 | C4: 4000 | D4: 350 | E4: 0.99 | F4: 10
A5: M4 | B5: 3000 | C5: 4000 | D5: 350 | E5: 0.99 | F5: 10
A6: M5 | B6: 3000 | C6: 4000 | D6: 350 | E6: 0.99 | F6: 10
A7: M6 | B7: 3000 | C7: 4000 | D7: 350 | E7: 0.99 | F7: 10
A8: M7 | B8: 3000 | C8: 4000 | D8: 350 | E8: 0.99 | F8: 10
A9: M8 | B9: 3000 | C9: 4000 | D9: 350 | E9: 0.99 | F9: 10
A10: M9 | B10: 3000 | C10: 4000 | D10: 350 | E10: 0.99 | F10: 10
A11: M10 | B11: 3000 | C11: 4000 | D11: 350 | E11: 0.99 | F11: 10
A12: M11 | B12: 3000 | C12: 4000 | D12: 350 | E12: 0.99 | F12: 10
A13: M12 | B13: 3000 | C13: 4000 | D13: 350 | E13: 0.99 | F13: 10
A14: M13 (newest) | B14: 3000 | C14: 4000 | D14: 350 | E14: 0.99 | F14: 10

Sheet P&L
A1: MONTHLY P&L (computed from the Inputs tabs)
A2: Costs negative. TTM = the newest 12 months (columns C:N). All values flow from the Inputs_* tabs.
A3: Line item | B3: M1 (ol | C3: M2 | D3: M3 | E3: M4 | F3: M5 | G3: M6 | H3: M7 | I3: M8 | J3: M9 | K3: M10 | L3: M11 | M3: M12 | N3: M13 (n | O3: TTM | P3: TTM avg
A4: REVENUE
A5: Product Sales | B5: =Inputs_Monthly!B2+Inputs_Monthly!C2 -> 5000 | C5: =Inputs_Monthly!B3+Inputs_Monthly!C3 -> 5000 | D5: =Inputs_Monthly!B4+Inputs_Monthly!C4 -> 5000 | E5: =Inputs_Monthly!B5+Inputs_Monthly!C5 -> 5000 | F5: =Inputs_Monthly!B6+Inputs_Monthly!C6 -> 5000 | G5: =Inputs_Monthly!B7+Inputs_Monthly!C7 -> 5000 | H5: =Inputs_Monthly!B8+Inputs_Monthly!C8 -> 5000 | I5: =Inputs_Monthly!B9+Inputs_Monthly!C9 -> 5000 | J5: =Inputs_Monthly!B10+Inputs_Monthly!C10 -> 5000 | K5: =Inputs_Monthly!B11+Inputs_Monthly!C11 -> 5000 | L5: =Inputs_Monthly!B12+Inputs_Monthly!C12 -> 5000 | M5: =Inputs_Monthly!B13+Inputs_Monthly!C13 -> 5000 | N5: =Inputs_Monthly!B14+Inputs_Monthly!C14 -> 5000 | O5: =SUM(C5:N5) -> 60000 | P5: =O5/12 -> 5000
A6: Other Income (postage, inv, gift) | B6: =Inputs_Monthly!G2+Inputs_Monthly!H2+Inputs_Monthly!I2 -> 156 | C6: =Inputs_Monthly!G3+Inputs_Monthly!H3+Inputs_Monthly!I3 -> 156 | D6: =Inputs_Monthly!G4+Inputs_Monthly!H4+Inputs_Monthly!I4 -> 156 | E6: =Inputs_Monthly!G5+Inputs_Monthly!H5+Inputs_Monthly!I5 -> 156 | F6: =Inputs_Monthly!G6+Inputs_Monthly!H6+Inputs_Monthly!I6 -> 156 | G6: =Inputs_Monthly!G7+Inputs_Monthly!H7+Inputs_Monthly!I7 -> 156 | H6: =Inputs_Monthly!G8+Inputs_Monthly!H8+Inputs_Monthly!I8 -> 156 | I6: =Inputs_Monthly!G9+Inputs_Monthly!H9+Inputs_Monthly!I9 -> 156 | J6: =Inputs_Monthly!G10+Inputs_Monthly!H10+Inputs_Monthly!I10 -> 156 | K6: =Inputs_Monthly!G11+Inputs_Monthly!H11+Inputs_Monthly!I11 -> 156 | L6: =Inputs_Monthly!G12+Inputs_Monthly!H12+Inputs_Monthly!I12 -> 156 | M6: =Inputs_Monthly!G13+Inputs_Monthly!H13+Inputs_Monthly!I13 -> 156 | N6: =Inputs_Monthly!G14+Inputs_Monthly!H14+Inputs_Monthly!I14 -> 156 | O6: =SUM(C6:N6) -> 1872 | P6: =O6/12 -> 156
A7: less: Promotional Rebates (net) | B7: =Inputs_Monthly!J2+Inputs_Monthly!K2 -> -98 | C7: =Inputs_Monthly!J3+Inputs_Monthly!K3 -> -98 | D7: =Inputs_Monthly!J4+Inputs_Monthly!K4 -> -98 | E7: =Inputs_Monthly!J5+Inputs_Monthly!K5 -> -98 | F7: =Inputs_Monthly!J6+Inputs_Monthly!K6 -> -98 | G7: =Inputs_Monthly!J7+Inputs_Monthly!K7 -> -98 | H7: =Inputs_Monthly!J8+Inputs_Monthly!K8 -> -98 | I7: =Inputs_Monthly!J9+Inputs_Monthly!K9 -> -98 | J7: =Inputs_Monthly!J10+Inputs_Monthly!K10 -> -98 | K7: =Inputs_Monthly!J11+Inputs_Monthly!K11 -> -98 | L7: =Inputs_Monthly!J12+Inputs_Monthly!K12 -> -98 | M7: =Inputs_Monthly!J13+Inputs_Monthly!K13 -> -98 | N7: =Inputs_Monthly!J14+Inputs_Monthly!K14 -> -98 | O7: =SUM(C7:N7) -> -1176 | P7: =O7/12 -> -98
A8: less: Returns & Refunds | B8: =Inputs_Monthly!D2+Inputs_Monthly!E2+Inputs_Monthly!F2 -> -155 | C8: =Inputs_Monthly!D3+Inputs_Monthly!E3+Inputs_Monthly!F3 -> -155 | D8: =Inputs_Monthly!D4+Inputs_Monthly!E4+Inputs_Monthly!F4 -> -155 | E8: =Inputs_Monthly!D5+Inputs_Monthly!E5+Inputs_Monthly!F5 -> -155 | F8: =Inputs_Monthly!D6+Inputs_Monthly!E6+Inputs_Monthly!F6 -> -155 | G8: =Inputs_Monthly!D7+Inputs_Monthly!E7+Inputs_Monthly!F7 -> -155 | H8: =Inputs_Monthly!D8+Inputs_Monthly!E8+Inputs_Monthly!F8 -> -155 | I8: =Inputs_Monthly!D9+Inputs_Monthly!E9+Inputs_Monthly!F9 -> -155 | J8: =Inputs_Monthly!D10+Inputs_Monthly!E10+Inputs_Monthly!F10 -> -155 | K8: =Inputs_Monthly!D11+Inputs_Monthly!E11+Inputs_Monthly!F11 -> -155 | L8: =Inputs_Monthly!D12+Inputs_Monthly!E12+Inputs_Monthly!F12 -> -155 | M8: =Inputs_Monthly!D13+Inputs_Monthly!E13+Inputs_Monthly!F13 -> -155 | N8: =Inputs_Monthly!D14+Inputs_Monthly!E14+Inputs_Monthly!F14 -> -155 | O8: =SUM(C8:N8) -> -1860 | P8: =O8/12 -> -155
A9: Net Sales | B9: =SUM(B5:B8) -> 4903 | C9: =SUM(C5:C8) -> 4903 | D9: =SUM(D5:D8) -> 4903 | E9: =SUM(E5:E8) -> 4903 | F9: =SUM(F5:F8) -> 4903 | G9: =SUM(G5:G8) -> 4903 | H9: =SUM(H5:H8) -> 4903 | I9: =SUM(I5:I8) -> 4903 | ... N9: =SUM(N5:N8) -> 4903 | O9: =SUM(C9:N9) -> 58836 | P9: =O9/12 -> 4903
A10: check: Income total (PDF) | B10: =Inputs_Monthly!L2 -> 4903 | C10: =Inputs_Monthly!L3 -> 4903 | D10: =Inputs_Monthly!L4 -> 4903 | E10: =Inputs_Monthly!L5 -> 4903 | F10: =Inputs_Monthly!L6 -> 4903 | G10: =Inputs_Monthly!L7 -> 4903 | H10: =Inputs_Monthly!L8 -> 4903 | I10: =Inputs_Monthly!L9 -> 4903 | J10: =Inputs_Monthly!L10 -> 4903 | K10: =Inputs_Monthly!L11 -> 4903 | L10: =Inputs_Monthly!L12 -> 4903 | M10: =Inputs_Monthly!L13 -> 4903 | N10: =Inputs_Monthly!L14 -> 4903
A11: check: Difference (0) | B11: =B9-B10 -> 0 | C11: =C9-C10 -> 0 | D11: =D9-D10 -> 0 | E11: =E9-E10 -> 0 | F11: =F9-F10 -> 0 | G11: =G9-G10 -> 0 | H11: =H9-H10 -> 0 | I11: =I9-I10 -> 0 | ... N11: =N9-N10 -> 0
A13: AMAZON FEES (referral & FBA split net + VAT@20%)
A14: Referral / Selling Fees (ex-VAT) | B14: =(Inputs_Monthly!M2+Inputs_Monthly!N2+Inputs_Monthly!O2)/1.2 -> -620.83333 | C14: =(Inputs_Monthly!M3+Inputs_Monthly!N3+Inputs_Monthly!O3)/1.2 -> -620.83333 | D14: =(Inputs_Monthly!M4+Inputs_Monthly!N4+Inputs_Monthly!O4)/1.2 -> -620.83333 | E14: =(Inputs_Monthly!M5+Inputs_Monthly!N5+Inputs_Monthly!O5)/1.2 -> -620.83333 | F14: =(Inputs_Monthly!M6+Inputs_Monthly!N6+Inputs_Monthly!O6)/1.2 -> -620.83333 | G14: =(Inputs_Monthly!M7+Inputs_Monthly!N7+Inputs_Monthly!O7)/1.2 -> -620.83333 | H14: =(Inputs_Monthly!M8+Inputs_Monthly!N8+Inputs_Monthly!O8)/1.2 -> -620.83333 | I14: =(Inputs_Monthly!M9+Inputs_Monthly!N9+Inputs_Monthly!O9)/1.2 -> -620.83333 | J14: =(Inputs_Monthly!M10+Inputs_Monthly!N10+Inputs_Monthly!O10)/1.2 -> -620.83333 | K14: =(Inputs_Monthly!M11+Inputs_Monthly!N11+Inputs_Monthly!O11)/1.2 -> -620.83333 | L14: =(Inputs_Monthly!M12+Inputs_Monthly!N12+Inputs_Monthly!O12)/1.2 -> -620.83333 | M14: =(Inputs_Monthly!M13+Inputs_Monthly!N13+Inputs_Monthly!O13)/1.2 -> -620.83333 | N14: =(Inputs_Monthly!M14+Inputs_Monthly!N14+Inputs_Monthly!O14)/1.2 -> -620.83333 | O14: =SUM(C14:N14) -> -7450 | P14: =O14/12 -> -620.83333
A15: Referral Fees — VAT @20% | B15: =(Inputs_Monthly!M2+Inputs_Monthly!N2+Inputs_Monthly!O2)-B14 -> -124.16667 | C15: =(Inputs_Monthly!M3+Inputs_Monthly!N3+Inputs_Monthly!O3)-C14 -> -124.16667 | D15: =(Inputs_Monthly!M4+Inputs_Monthly!N4+Inputs_Monthly!O4)-D14 -> -124.16667 | E15: =(Inputs_Monthly!M5+Inputs_Monthly!N5+Inputs_Monthly!O5)-E14 -> -124.16667 | F15: =(Inputs_Monthly!M6+Inputs_Monthly!N6+Inputs_Monthly!O6)-F14 -> -124.16667 | G15: =(Inputs_Monthly!M7+Inputs_Monthly!N7+Inputs_Monthly!O7)-G14 -> -124.16667 | H15: =(Inputs_Monthly!M8+Inputs_Monthly!N8+Inputs_Monthly!O8)-H14 -> -124.16667 | I15: =(Inputs_Monthly!M9+Inputs_Monthly!N9+Inputs_Monthly!O9)-I14 -> -124.16667 | J15: =(Inputs_Monthly!M10+Inputs_Monthly!N10+Inputs_Monthly!O10)-J14 -> -124.16667 | K15: =(Inputs_Monthly!M11+Inputs_Monthly!N11+Inputs_Monthly!O11)-K14 -> -124.16667 | L15: =(Inputs_Monthly!M12+Inputs_Monthly!N12+Inputs_Monthly!O12)-L14 -> -124.16667 | M15: =(Inputs_Monthly!M13+Inputs_Monthly!N13+Inputs_Monthly!O13)-M14 -> -124.16667 | N15: =(Inputs_Monthly!M14+Inputs_Monthly!N14+Inputs_Monthly!O14)-N14 -> -124.16667 | O15: =SUM(C15:N15) -> -1490 | P15: =O15/12 -> -124.16667
A16: FBA Fulfilment Fees (ex-VAT) | B16: =(Inputs_Monthly!P2+Inputs_Monthly!Q2)/1.2 -> -997.5 | C16: =(Inputs_Monthly!P3+Inputs_Monthly!Q3)/1.2 -> -997.5 | D16: =(Inputs_Monthly!P4+Inputs_Monthly!Q4)/1.2 -> -997.5 | E16: =(Inputs_Monthly!P5+Inputs_Monthly!Q5)/1.2 -> -997.5 | F16: =(Inputs_Monthly!P6+Inputs_Monthly!Q6)/1.2 -> -997.5 | G16: =(Inputs_Monthly!P7+Inputs_Monthly!Q7)/1.2 -> -997.5 | H16: =(Inputs_Monthly!P8+Inputs_Monthly!Q8)/1.2 -> -997.5 | I16: =(Inputs_Monthly!P9+Inputs_Monthly!Q9)/1.2 -> -997.5 | J16: =(Inputs_Monthly!P10+Inputs_Monthly!Q10)/1.2 -> -997.5 | K16: =(Inputs_Monthly!P11+Inputs_Monthly!Q11)/1.2 -> -997.5 | L16: =(Inputs_Monthly!P12+Inputs_Monthly!Q12)/1.2 -> -997.5 | M16: =(Inputs_Monthly!P13+Inputs_Monthly!Q13)/1.2 -> -997.5 | N16: =(Inputs_Monthly!P14+Inputs_Monthly!Q14)/1.2 -> -997.5 | O16: =SUM(C16:N16) -> -11970 | P16: =O16/12 -> -997.5
A17: FBA Fulfilment — VAT @20% | B17: =(Inputs_Monthly!P2+Inputs_Monthly!Q2)-B16 -> -199.5 | C17: =(Inputs_Monthly!P3+Inputs_Monthly!Q3)-C16 -> -199.5 | D17: =(Inputs_Monthly!P4+Inputs_Monthly!Q4)-D16 -> -199.5 | E17: =(Inputs_Monthly!P5+Inputs_Monthly!Q5)-E16 -> -199.5 | F17: =(Inputs_Monthly!P6+Inputs_Monthly!Q6)-F16 -> -199.5 | G17: =(Inputs_Monthly!P7+Inputs_Monthly!Q7)-G16 -> -199.5 | H17: =(Inputs_Monthly!P8+Inputs_Monthly!Q8)-H16 -> -199.5 | I17: =(Inputs_Monthly!P9+Inputs_Monthly!Q9)-I16 -> -199.5 | J17: =(Inputs_Monthly!P10+Inputs_Monthly!Q10)-J16 -> -199.5 | K17: =(Inputs_Monthly!P11+Inputs_Monthly!Q11)-K16 -> -199.5 | L17: =(Inputs_Monthly!P12+Inputs_Monthly!Q12)-L16 -> -199.5 | M17: =(Inputs_Monthly!P13+Inputs_Monthly!Q13)-M16 -> -199.5 | N17: =(Inputs_Monthly!P14+Inputs_Monthly!Q14)-N16 -> -199.5 | O17: =SUM(C17:N17) -> -2394 | P17: =O17/12 -> -199.5
A18: Storage & Inbound Fees (incl VAT) | B18: =Inputs_Monthly!T2 -> -150 | C18: =Inputs_Monthly!T3 -> -150 | D18: =Inputs_Monthly!T4 -> -150 | E18: =Inputs_Monthly!T5 -> -150 | F18: =Inputs_Monthly!T6 -> -150 | G18: =Inputs_Monthly!T7 -> -150 | H18: =Inputs_Monthly!T8 -> -150 | I18: =Inputs_Monthly!T9 -> -150 | J18: =Inputs_Monthly!T10 -> -150 | K18: =Inputs_Monthly!T11 -> -150 | L18: =Inputs_Monthly!T12 -> -150 | M18: =Inputs_Monthly!T13 -> -150 | N18: =Inputs_Monthly!T14 -> -150 | O18: =SUM(C18:N18) -> -1800 | P18: =O18/12 -> -150
A19: Other Fees (incl VAT) | B19: =Inputs_Monthly!R2+Inputs_Monthly!S2+Inputs_Monthly!U2+Inputs_Monthly!V2+Inputs_Monthly!W2+Inputs_Monthly!X2 -> -71.5 | C19: =Inputs_Monthly!R3+Inputs_Monthly!S3+Inputs_Monthly!U3+Inputs_Monthly!V3+Inputs_Monthly!W3+Inputs_Monthly!X3 -> -71.5 | D19: =Inputs_Monthly!R4+Inputs_Monthly!S4+Inputs_Monthly!U4+Inputs_Monthly!V4+Inputs_Monthly!W4+Inputs_Monthly!X4 -> -71.5 | E19: =Inputs_Monthly!R5+Inputs_Monthly!S5+Inputs_Monthly!U5+Inputs_Monthly!V5+Inputs_Monthly!W5+Inputs_Monthly!X5 -> -71.5 | F19: =Inputs_Monthly!R6+Inputs_Monthly!S6+Inputs_Monthly!U6+Inputs_Monthly!V6+Inputs_Monthly!W6+Inputs_Monthly!X6 -> -71.5 | G19: =Inputs_Monthly!R7+Inputs_Monthly!S7+Inputs_Monthly!U7+Inputs_Monthly!V7+Inputs_Monthly!W7+Inputs_Monthly!X7 -> -71.5 | H19: =Inputs_Monthly!R8+Inputs_Monthly!S8+Inputs_Monthly!U8+Inputs_Monthly!V8+Inputs_Monthly!W8+Inputs_Monthly!X8 -> -71.5 | I19: =Inputs_Monthly!R9+Inputs_Monthly!S9+Inputs_Monthly!U9+Inputs_Monthly!V9+Inputs_Monthly!W9+Inputs_Monthly!X9 -> -71.5 | J19: =Inputs_Monthly!R10+Inputs_Monthly!S10+Inputs_Monthly!U10+Inputs_Monthly!V10+Inputs_Monthly!W10+Inputs_Monthly!X10 -> -71.5 | K19: =Inputs_Monthly!R11+Inputs_Monthly!S11+Inputs_Monthly!U11+Inputs_Monthly!V11+Inputs_Monthly!W11+Inputs_Monthly!X11 -> -71.5 | L19: =Inputs_Monthly!R12+Inputs_Monthly!S12+Inputs_Monthly!U12+Inputs_Monthly!V12+Inputs_Monthly!W12+Inputs_Monthly!X12 -> -71.5 | M19: =Inputs_Monthly!R13+Inputs_Monthly!S13+Inputs_Monthly!U13+Inputs_Monthly!V13+Inputs_Monthly!W13+Inputs_Monthly!X13 -> -71.5 | N19: =Inputs_Monthly!R14+Inputs_Monthly!S14+Inputs_Monthly!U14+Inputs_Monthly!V14+Inputs_Monthly!W14+Inputs_Monthly!X14 -> -71.5 | O19: =SUM(C19:N19) -> -858 | P19: =O19/12 -> -71.5
A20: Total Amazon Fees (incl VAT, excl ads) | B20: =SUM(B14:B19) -> -2163.5 | C20: =SUM(C14:C19) -> -2163.5 | D20: =SUM(D14:D19) -> -2163.5 | E20: =SUM(E14:E19) -> -2163.5 | F20: =SUM(F14:F19) -> -2163.5 | G20: =SUM(G14:G19) -> -2163.5 | H20: =SUM(H14:H19) -> -2163.5 | I20: =SUM(I14:I19) -> -2163.5 | ... N20: =SUM(N14:N19) -> -2163.5 | O20: =SUM(C20:N20) -> -25962 | P20: =O20/12 -> -2163.5
A22: ADVERTISING / PPC
A23: PPC / Advertising (ex-VAT) | B23: =Inputs_Monthly!Y2/1.2 -> -500 | C23: =Inputs_Monthly!Y3/1.2 -> -500 | D23: =Inputs_Monthly!Y4/1.2 -> -500 | E23: =Inputs_Monthly!Y5/1.2 -> -500 | F23: =Inputs_Monthly!Y6/1.2 -> -500 | G23: =Inputs_Monthly!Y7/1.2 -> -500 | H23: =Inputs_Monthly!Y8/1.2 -> -500 | I23: =Inputs_Monthly!Y9/1.2 -> -500 | J23: =Inputs_Monthly!Y10/1.2 -> -500 | K23: =Inputs_Monthly!Y11/1.2 -> -500 | L23: =Inputs_Monthly!Y12/1.2 -> -500 | M23: =Inputs_Monthly!Y13/1.2 -> -500 | N23: =Inputs_Monthly!Y14/1.2 -> -500 | O23: =SUM(C23:N23) -> -6000 | P23: =O23/12 -> -500
A24: PPC — VAT @20% | B24: =Inputs_Monthly!Y2-B23 -> -100 | C24: =Inputs_Monthly!Y3-C23 -> -100 | D24: =Inputs_Monthly!Y4-D23 -> -100 | E24: =Inputs_Monthly!Y5-E23 -> -100 | F24: =Inputs_Monthly!Y6-F23 -> -100 | G24: =Inputs_Monthly!Y7-G23 -> -100 | H24: =Inputs_Monthly!Y8-H23 -> -100 | I24: =Inputs_Monthly!Y9-I23 -> -100 | J24: =Inputs_Monthly!Y10-J23 -> -100 | K24: =Inputs_Monthly!Y11-K23 -> -100 | L24: =Inputs_Monthly!Y12-L23 -> -100 | M24: =Inputs_Monthly!Y13-M23 -> -100 | N24: =Inputs_Monthly!Y14-N23 -> -100 | O24: =SUM(C24:N24) -> -1200 | P24: =O24/12 -> -100
A25: Total PPC (incl VAT) | B25: =B23+B24 -> -600 | C25: =C23+C24 -> -600 | D25: =D23+D24 -> -600 | E25: =E23+E24 -> -600 | F25: =F23+F24 -> -600 | G25: =G23+G24 -> -600 | H25: =H23+H24 -> -600 | I25: =I23+I24 -> -600 | ... N25: =N23+N24 -> -600 | O25: =SUM(C25:N25) -> -7200 | P25: =O25/12 -> -600
A26: check: Expenses total (PDF) | B26: =Inputs_Monthly!Z2 -> -2763.5 | C26: =Inputs_Monthly!Z3 -> -2763.5 | D26: =Inputs_Monthly!Z4 -> -2763.5 | E26: =Inputs_Monthly!Z5 -> -2763.5 | F26: =Inputs_Monthly!Z6 -> -2763.5 | G26: =Inputs_Monthly!Z7 -> -2763.5 | H26: =Inputs_Monthly!Z8 -> -2763.5 | I26: =Inputs_Monthly!Z9 -> -2763.5 | J26: =Inputs_Monthly!Z10 -> -2763.5 | K26: =Inputs_Monthly!Z11 -> -2763.5 | L26: =Inputs_Monthly!Z12 -> -2763.5 | M26: =Inputs_Monthly!Z13 -> -2763.5 | N26: =Inputs_Monthly!Z14 -> -2763.5
A27: check: Difference (0) | B27: =(B20+B25)-B26 -> 0 | C27: =(C20+C25)-C26 -> 0 | D27: =(D20+D25)-D26 -> 0 | E27: =(E20+E25)-E26 -> 0 | F27: =(F20+F25)-F26 -> 0 | G27: =(G20+G25)-G26 -> 0 | H27: =(H20+H25)-H26 -> 0 | I27: =(I20+I25)-I26 -> 0 | ... N27: =(N20+N25)-N26 -> 0
A29: COGS, VAT & NET PROFIT
A30: Units Sold (net) | B30: =Inputs_Units!D32 -> 350 | C30: =Inputs_Units!E32 -> 350 | D30: =Inputs_Units!F32 -> 350 | E30: =Inputs_Units!G32 -> 350 | F30: =Inputs_Units!H32 -> 350 | G30: =Inputs_Units!I32 -> 350 | H30: =Inputs_Units!J32 -> 350 | I30: =Inputs_Units!K32 -> 350 | ... N30: =Inputs_Units!P32 -> 350 | O30: =SUM(C30:N30) -> 4200 | P30: =O30/12 -> 350
A31: Avg Selling Price | B31: =IFERROR(B5/B30,0) -> 14.285714 | C31: =IFERROR(C5/C30,0) -> 14.285714 | D31: =IFERROR(D5/D30,0) -> 14.285714 | E31: =IFERROR(E5/E30,0) -> 14.285714 | F31: =IFERROR(F5/F30,0) -> 14.285714 | G31: =IFERROR(G5/G30,0) -> 14.285714 | H31: =IFERROR(H5/H30,0) -> 14.285714 | I31: =IFERROR(I5/I30,0) -> 14.285714 | ... N31: =IFERROR(N5/N30,0) -> 14.285714
A32: COGS (DDP + import VAT) | B32: =-Inputs_Units!D33 -> -650 | C32: =-Inputs_Units!E33 -> -650 | D32: =-Inputs_Units!F33 -> -650 | E32: =-Inputs_Units!G33 -> -650 | F32: =-Inputs_Units!H33 -> -650 | G32: =-Inputs_Units!I33 -> -650 | H32: =-Inputs_Units!J33 -> -650 | I32: =-Inputs_Units!K33 -> -650 | ... N32: =-Inputs_Units!P33 -> -650 | O32: =SUM(C32:N32) -> -7800 | P32: =O32/12 -> -650
A33: Output VAT (per VAT status) | B33: =-B9/6*$B$45 -> 0 | C33: =-C9/6*$B$45 -> 0 | D33: =-D9/6*$B$45 -> 0 | E33: =-E9/6*$B$45 -> 0 | F33: =-F9/6*$B$45 -> 0 | G33: =-G9/6*$B$45 -> 0 | H33: =-H9/6*$B$45 -> 0 | I33: =-I9/6*$B$45 -> 0 | ... N33: =-N9/6*$B$45 -> 0 | O33: =SUM(C33:N33) -> 0 | P33: =O33/12 -> 0
A34: Off-Amazon Operating Costs | B34: =-$B$44 -> 0 | C34: =-$B$44 -> 0 | D34: =-$B$44 -> 0 | E34: =-$B$44 -> 0 | F34: =-$B$44 -> 0 | G34: =-$B$44 -> 0 | H34: =-$B$44 -> 0 | I34: =-$B$44 -> 0 | ... N34: =-$B$44 -> 0 | O34: =SUM(C34:N34) -> 0 | P34: =O34/12 -> 0
A35: Estimated Net Profit | B35: =B9+B20+B25+B32+B33+B34 -> 1489.5 | C35: =C9+C20+C25+C32+C33+C34 -> 1489.5 | D35: =D9+D20+D25+D32+D33+D34 -> 1489.5 | E35: =E9+E20+E25+E32+E33+E34 -> 1489.5 | F35: =F9+F20+F25+F32+F33+F34 -> 1489.5 | G35: =G9+G20+G25+G32+G33+G34 -> 1489.5 | H35: =H9+H20+H25+H32+H33+H34 -> 1489.5 | I35: =I9+I20+I25+I32+I33+I34 -> 1489.5 | ... N35: =N9+N20+N25+N32+N33+N34 -> 1489.5 | O35: =SUM(C35:N35) -> 17874 | P35: =O35/12 -> 1489.5
A36: KEY METRICS
A37: TACoS % | B37: =IFERROR(-B25/B9,0) -> 0.12237406 | C37: =IFERROR(-C25/C9,0) -> 0.12237406 | D37: =IFERROR(-D25/D9,0) -> 0.12237406 | E37: =IFERROR(-E25/E9,0) -> 0.12237406 | F37: =IFERROR(-F25/F9,0) -> 0.12237406 | G37: =IFERROR(-G25/G9,0) -> 0.12237406 | H37: =IFERROR(-H25/H9,0) -> 0.12237406 | I37: =IFERROR(-I25/I9,0) -> 0.12237406 | ... O37: =IFERROR(-O25/O9,0) -> 0.12237406
A38: Amazon fee % of net sales | B38: =IFERROR(-B20/B9,0) -> 0.44126045 | C38: =IFERROR(-C20/C9,0) -> 0.44126045 | D38: =IFERROR(-D20/D9,0) -> 0.44126045 | E38: =IFERROR(-E20/E9,0) -> 0.44126045 | F38: =IFERROR(-F20/F9,0) -> 0.44126045 | G38: =IFERROR(-G20/G9,0) -> 0.44126045 | H38: =IFERROR(-H20/H9,0) -> 0.44126045 | I38: =IFERROR(-I20/I9,0) -> 0.44126045 | ... O38: =IFERROR(-O20/O9,0) -> 0.44126045
A39: Net margin % | B39: =IFERROR(B35/B9,0) -> 0.3037936 | C39: =IFERROR(C35/C9,0) -> 0.3037936 | D39: =IFERROR(D35/D9,0) -> 0.3037936 | E39: =IFERROR(E35/E9,0) -> 0.3037936 | F39: =IFERROR(F35/F9,0) -> 0.3037936 | G39: =IFERROR(G35/G9,0) -> 0.3037936 | H39: =IFERROR(H35/H9,0) -> 0.3037936 | I39: =IFERROR(I35/I9,0) -> 0.3037936 | ... O39: =IFERROR(O35/O9,0) -> 0.3037936
A42: ASSUMPTIONS
A43: Blended landed £/unit (computed) | B43: =IFERROR(-O32/O30,0) -> 1.8571429
A44: Off-Amazon operating cost (£/month) | B44: 0
A45: VAT registered & standard-rated? (1=yes,0=no) | B45: 0

Sheet Summary
B2: SUMMARY (TTM)
B4: Net Sales (TTM) | C4: ='P&L'!O9 -> 58836
B5: Total Amazon Fees incl VAT | C5: ='P&L'!O20 -> -25962
B6: PPC incl VAT | C6: ='P&L'!O25 -> -7200
B7: COGS | C7: ='P&L'!O32 -> -7800
B8: Output VAT | C8: ='P&L'!O33 -> 0
B9: Off-Amazon OpEx (TTM) | C9: ='P&L'!O34 -> 0
B10: NET PROFIT (TTM) | C10: ='P&L'!O35 -> 17874
B11: Net margin % | C11: ='P&L'!O39 -> 0.3037936
B12: Blended landed £/unit | C12: ='P&L'!B43 -> 1.8571429
B14: Asking Price (enter) | C14: 0
B15: Implied multiple (Price ÷ Net Profit) | C15: =IFERROR(C14/'P&L'!O35,0) -> 0
